app/__init__.py
app/app.py
app/function/__init__.py
app/function/function_code.py
app/resource/__init__.py
app/resource/config.py
jdoc-0.0.4.dist-info/LICENSE.txt
jdoc-0.0.4.dist-info/METADATA
jdoc-0.0.4.dist-info/WHEEL
jdoc-0.0.4.dist-info/entry_points.txt
jdoc-0.0.4.dist-info/top_level.txt
jdoc-0.0.4.dist-info/RECORD
