Metadata-Version: 2.1
Name: jdoc
Version: 0.0.4
Summary: java document search engine
Home-page: https://github.com/sheng-kai-wang/java-doc-search-engine
Author: ['sheng-kai-wang', 'Chung-Chieh-Li', 'hsih-min-tang', 'chun-kai-yang']
Author-email: nssh94879487@gmail.com
License: UNKNOWN
Platform: UNKNOWN
Classifier: Programming Language :: Python :: 3
Classifier: License :: OSI Approved :: MIT License
Classifier: Operating System :: OS Independent
Requires-Python: >=3.6
License-File: LICENSE.txt
Requires-Dist: pyfiglet (==0.8.post1)
Requires-Dist: click (==8.1.3)
Requires-Dist: jsonpath (==0.82)
Requires-Dist: nltk (==3.7)
Requires-Dist: numpy (==1.22.4)
Requires-Dist: pandas (==1.4.2)
Requires-Dist: regex (==2022.6.2)
